YansuanfaBiji201710/README.md
YansuanfaBiji201710/__init__.py
YansuanfaBiji201710/__main__.py
YansuanfaBiji201710/file.epub
YansuanfaBiji201710/index.html
YansuanfaBiji201710/css/__init__.py
YansuanfaBiji201710/css/annotations.css
YansuanfaBiji201710/css/main.css
YansuanfaBiji201710/css/normalize.css
YansuanfaBiji201710/css/popup.css
YansuanfaBiji201710/font/__init__.py
YansuanfaBiji201710/font/fontello.eot
YansuanfaBiji201710/font/fontello.svg
YansuanfaBiji201710/font/fontello.ttf
YansuanfaBiji201710/font/fontello.woff
YansuanfaBiji201710/img/__init__.py
YansuanfaBiji201710/img/annotator-glyph-sprite.png
YansuanfaBiji201710/img/annotator-icon-sprite.png
YansuanfaBiji201710/img/apple-touch-icon.png
YansuanfaBiji201710/img/cancelfullscreen.png
YansuanfaBiji201710/img/close.png
YansuanfaBiji201710/img/fullscreen.png
YansuanfaBiji201710/img/loader.gif
YansuanfaBiji201710/img/menu-icon.png
YansuanfaBiji201710/img/save.png
YansuanfaBiji201710/img/saved.png
YansuanfaBiji201710/img/settings-s.png
YansuanfaBiji201710/img/settings.png
YansuanfaBiji201710/img/star.png
YansuanfaBiji201710/js/__init__.py
YansuanfaBiji201710/js/epub.js
YansuanfaBiji201710/js/epub.min.js
YansuanfaBiji201710/js/epub.min.map
YansuanfaBiji201710/js/hooks.min.js
YansuanfaBiji201710/js/hooks.min.map
YansuanfaBiji201710/js/reader.js
YansuanfaBiji201710/js/reader.js.map
YansuanfaBiji201710/js/reader.min.js
YansuanfaBiji201710/js/reader.min.map
YansuanfaBiji201710/js/hooks/__init__.py
YansuanfaBiji201710/js/hooks/extensions/__init__.py
YansuanfaBiji201710/js/hooks/extensions/highlight.js
YansuanfaBiji201710/js/libs/__init__.py
YansuanfaBiji201710/js/libs/jquery.min.js
YansuanfaBiji201710/js/libs/localforage.min.js
YansuanfaBiji201710/js/libs/screenfull.js
YansuanfaBiji201710/js/libs/screenfull.min.js
YansuanfaBiji201710/js/libs/zip.min.js
YansuanfaBiji201710/js/plugins/__init__.py
YansuanfaBiji201710/js/plugins/hypothesis.js
YansuanfaBiji201710/js/plugins/search.js
yansuanfa_biji_201710-2024.3.2.0.dist-info/METADATA
yansuanfa_biji_201710-2024.3.2.0.dist-info/WHEEL
yansuanfa_biji_201710-2024.3.2.0.dist-info/entry_points.txt
yansuanfa_biji_201710-2024.3.2.0.dist-info/top_level.txt
yansuanfa_biji_201710-2024.3.2.0.dist-info/RECORD
